Metadata-Version: 2.4
Name: adafruit-circuitpython-ens160
Version: 1.0.13
Summary: CircuitPython / Python library for ScioSense ENS160 digital multi-gas sensor
Author-email: Adafruit Industries <circuitpython@adafruit.com>
License: MIT
Project-URL: Homepage, https://github.com/adafruit/Adafruit_CircuitPython_ENS160
Keywords: adafruit,blinka,circuitpython,micropython,ens160,ens160,python,circuitpython,gas,tvoc,eco2,mox,sensor
Classifier: Intended Audience :: Developers
Classifier: Topic :: Software Development :: Libraries
Classifier: Topic :: Software Development :: Embedded Systems
Classifier: Topic :: System :: Hardware
Classifier: License :: OSI Approved :: MIT License
Classifier: Programming Language :: Python :: 3
License-File: LICENSE
Requires-Dist: Adafruit-Blinka
Requires-Dist: adafruit-circuitpython-busdevice
Requires-Dist: adafruit-circuitpython-register
Requires-Dist: typing-extensions~=4.0
Provides-Extra: optional
Dynamic: license-file
